{
  "https://www.quora.com/profile/Alex-Tsepko/answers/published": {
    "name": "Alex",
    "title": "Why is taking photos every day so important?",
    "email": "admather@uiowa.edu"
  },
  "https://www.quora.com/profile/Amy-K-Stanton-1/answers/published": {
    "name": "Amy",
    "title": "",
    "email": "drew@digitalpress.com"
  },
  "https://www.quora.com/profile/Apolo-Ohno/answers/published": {
    "name": "Apolo",
    "title": "",
    "email": "drew@digitalpress.com"
  },
  "https://www.quora.com/profile/Barry-Kayton/answers/published": {
    "name": "Barry",
    "title": "",
    "email": "drew@digitalpress.com"
  },
  "https://www.quora.com/profile/Brian-Greenberg-10/answers/published": {
    "name": "Brian",
    "title": "What lessons have you learned from working in a family business?",
    "email": "drew@digitalpress.com"
  },
  "https://www.quora.com/profile/Christian-Spletzer/answers/published": {
    "name": "Christian",
    "title": "What makes a great recruiter?",
    "email": "drew@digitalpress.com"
  },
  "https://www.quora.com/profile/Christopher-Lochhead/answers/published": {
    "name": "Christopher",
    "title": "",
    "email": "drew@digitalpress.com"
  },
  "https://www.quora.com/profile/Dean-Graziosi-8/answers/published": {
    "name": "Dean",
    "title": "",
    "email": "drew@digitalpress.com"
  },
  "https://www.quora.com/profile/Dennis-Zdonov/answers/published": {
    "name": "Dennis",
    "title": "What are some sleep hacks and tips?",
    "email": "drew@digitalpress.com"
  },
  "https://www.quora.com/profile/Funeralocity-Ed-Michael-Reggie/answers/published": {
    "name": "Ed",
    "title": "What are your thoughts on green funerals? Are they really green?",
    "email": "drew@digitalpress.com"
  },
  "https://www.quora.com/profile/Freeman-Fan/answers/published": {
    "name": "Freeman",
    "title": "What are the most effective methods indie game developers use to market their games?",
    "email": "drew@digitalpress.com"
  },
  "https://www.quora.com/profile/Heidi-Zak/answers/published": {
    "name": "Heidi",
    "title": "How do I combine digital marketing strategy with offline marketing strategy?",
    "email": "drew@digitalpress.com"
  },
  "https://www.quora.com/profile/Jaleh-Bisharat/answers/published": {
    "name": "Jaleh",
    "title": "",
    "email": "drew@digitalpress.com"
  },
  "https://www.quora.com/profile/Joe-Polish-2/answers/published": {
    "name": "Joe",
    "title": "",
    "email": "drew@digitalpress.com"
  },
  "https://www.quora.com/profile/Jon-Shalowitz/answers/published": {
    "name": "Jon",
    "title": "How can I remain relevant when technology is advancing so rapidly?",
    "email": "drew@digitalpress.com"
  },
  "https://www.quora.com/profile/Josh-Fechter/answers/published": {
    "name": "Josh",
    "title": "Why are the founders of Instagram stepping down?",
    "email": "drew@digitalpress.com"
  },
  "https://www.quora.com/profile/Marc-Jones-17/answers/published": {
    "name": "Marc",
    "title": "",
    "email": "drew@digitalpress.com"
  },
  "https://www.quora.com/profile/Mark-Lurie/answers/published": {
    "name": "Mark",
    "title": "Why is there such a disconnect between Baby Boomers and Millennials when it comes to work ethic?",
    "email": "drew@digitalpress.com"
  },
  "https://www.quora.com/profile/Moshe-Joshua/answers/published": {
    "name": "Moshe",
    "title": "",
    "email": "drew@digitalpress.com"
  },
  "https://www.quora.com/profile/Nicolas-Susco/answers/published": {
    "name": "Nicolas",
    "title": "Does an entrepreneur need a creative mind?",
    "email": "drew@digitalpress.com"
  },
  "https://www.quora.com/profile/Pedram-Shojai/answers/published": {
    "name": "Pedram",
    "title": "",
    "email": "drew@digitalpress.com"
  },
  "https://www.quora.com/profile/Praveen-Tipirneni-MD/answers/published": {
    "name": "Praveen",
    "title": "How can the pharmaceutical industry be improved?",
    "email": "drew@digitalpress.com"
  },
  "https://www.quora.com/profile/Sam-Radocchia/answers/published": {
    "name": "Sam",
    "title": "When is the best time to change the job?",
    "email": "drew@digitalpress.com"
  },
  "https://www.quora.com/profile/Stephen-Goldmann-1/answers/published": {
    "name": "Stephen",
    "title": "",
    "email": "drew@digitalpress.com"
  },
  "https://www.quora.com/profile/Steven-Spatz/answers/published": {
    "name": "Steven",
    "title": "Which is the most efficient email marketing tool?",
    "email": "drew@digitalpress.com"
  },
  "https://www.quora.com/profile/Thomas-Korte/answers/published": {
    "name": "Thomas",
    "title": "",
    "email": "drew@digitalpress.com"
  }
}